setup.py
bamboo_weather/__init__.py
bamboo_weather/bamboo_weather.py
bamboo_weather_mxtchapanda.egg-info/PKG-INFO
bamboo_weather_mxtchapanda.egg-info/SOURCES.txt
bamboo_weather_mxtchapanda.egg-info/dependency_links.txt
bamboo_weather_mxtchapanda.egg-info/requires.txt
bamboo_weather_mxtchapanda.egg-info/top_level.txt