Metadata-Version: 2.1
Name: bamboo-weather-mxtchapanda
Version: 1.0.0
Summary: Simple Weather Package for Python
Author: Panda Bear
Author-email: mxtchapanda@gmail.com
Classifier: Development Status :: 3 - Alpha
Classifier: Intended Audience :: Developers
Classifier: Topic :: Software Development :: Build Tools
Classifier: License :: OSI Approved :: MIT License
Classifier: Programming Language :: Python :: 3.7
Classifier: Programming Language :: Python :: 3.8
Classifier: Programming Language :: Python :: 3.9
Classifier: Programming Language :: Python :: 3.10
Requires-Dist: requests
